odoo8_addon_survey_percent_question-8.0.0.1.0-py2.7-nspkg.pth
odoo8_addon_survey_percent_question-8.0.0.1.0.dist-info/top_level.txt
odoo8_addon_survey_percent_question-8.0.0.1.0.dist-info/WHEEL
odoo8_addon_survey_percent_question-8.0.0.1.0.dist-info/RECORD
odoo8_addon_survey_percent_question-8.0.0.1.0.dist-info/metadata.json
odoo8_addon_survey_percent_question-8.0.0.1.0.dist-info/DESCRIPTION.rst
odoo8_addon_survey_percent_question-8.0.0.1.0.dist-info/METADATA
odoo8_addon_survey_percent_question-8.0.0.1.0.dist-info/namespace_packages.txt
odoo_addons/survey_percent_question/__openerp__.py
odoo_addons/survey_percent_question/__init__.py
odoo_addons/survey_percent_question/README.rst
odoo_addons/survey_percent_question/models/survey_question.py
odoo_addons/survey_percent_question/models/__init__.py
odoo_addons/survey_percent_question/models/survey_input.py
odoo_addons/survey_percent_question/models/survey.py
odoo_addons/survey_percent_question/i18n/es.po
odoo_addons/survey_percent_question/i18n/hr.po
odoo_addons/survey_percent_question/i18n/sl.po
odoo_addons/survey_percent_question/i18n/survey_percent_question.pot
odoo_addons/survey_percent_question/i18n/de.po
odoo_addons/survey_percent_question/i18n/fr.po
odoo_addons/survey_percent_question/i18n/pt_BR.po
odoo_addons/survey_percent_question/views/survey_result.xml
odoo_addons/survey_percent_question/views/survey_templates.xml
odoo_addons/survey_percent_question/views/survey_views.xml
odoo_addons/survey_percent_question/controllers/main.py
odoo_addons/survey_percent_question/controllers/__init__.py
odoo_addons/survey_percent_question/tests/test_percent_question.py
odoo_addons/survey_percent_question/tests/__init__.py
